{
  "ehsId": "FMP008",
  "atlassianUserId": "5b10ac8d82e05b22cc7d4e07",
  "displayName": "Ryan O'Connor",
  "firstName": "Ryan",
  "lastName": "O'Connor",
  "email": "ryan.o'connor@fullmetalproductions.com",
  "accountType": "atlassian",
  "active": true,
  "projectRoles": [
    {
      "projectKey": "MMORPG",
      "projectName": "Fantasy Realm Online",
      "roles": [
        "Developer"
      ]
    },
    {
      "projectKey": "HORROR",
      "projectName": "Midnight Terror",
      "roles": [
        "Developer"
      ]
    },
    {
      "projectKey": "CYBR",
      "projectName": "CyberRealm",
      "roles": [
        "Developer"
      ]
    }
  ],
  "jiraGroups": [
    "jira-software-users",
    "development-team"
  ],
  "workloadSummary": {
    "assignedIssues": 19,
    "inProgressIssues": 1,
    "completedThisMonth": 6,
    "totalTimeLoggedThisMonth": "44h 16m",
    "averageTimePerIssue": "4h 8m"
  },
  "recentActivity": {
    "lastLogin": "2025-08-23T08:45:00Z",
    "issuesCreatedLastMonth": 5,
    "issuesResolvedLastMonth": 10,
    "commentsLastMonth": 12
  },
  "lastUpdated": "2025-08-23T10:30:00Z",
  "dataSource": "jira-userStats"
}