{
  "ehsId": "FMP022",
  "fileId": "SLK022",
  "upn": "isabella.white@fullmetalproductions.com",
  "firstName": "Isabella",
  "lastName": "White",
  "displayName": "Isabella White",
  "slackUserId": "U8819040426",
  "slackUsername": "isabella.white",
  "slackDisplayName": "Isabella White",
  "slackEmail": "isabella.white@fullmetalproductions.com",
  "activeSlackWorkspaces": [
    {
      "workspaceId": "T1234567890",
      "workspaceName": "Full Metal Productions",
      "workspaceDomain": "fullmetalproductions.slack.com",
      "membershipType": "regular",
      "joinedDate": "2021-04-15T09:00:00Z",
      "isActive": true,
      "lastActivity": "2025-08-23T08:45:00Z"
    }
  ],
  "activeSlackChannels": [
    {
      "channelId": "C5138851000",
      "channelName": "art-and-animation",
      "channelType": "private",
      "membershipType": "member",
      "joinedDate": "2021-04-15T10:00:00Z",
      "lastActivity": "2025-08-23T08:45:00Z",
      "messagesSentLastWeek": 11,
      "reactionsLastWeek": 12,
      "isArchived": false
    },
    {
      "channelId": "C2345678901",
      "channelName": "general",
      "channelType": "public",
      "membershipType": "member",
      "joinedDate": "2021-04-15T09:00:00Z",
      "lastActivity": "2025-08-22T16:30:00Z",
      "messagesSentLastWeek": 9,
      "reactionsLastWeek": 11,
      "isArchived": false
    }
  ],
  "activitySummary": {
    "totalChannels": 13,
    "totalDirectMessages": 5,
    "messagesSentLastWeek": 16,
    "reactionsLastWeek": 31,
    "filesSharedLastWeek": 1,
    "threadsStartedLastWeek": 4,
    "lastActiveDate": "2025-08-23T08:45:00Z",
    "averageDailyActivity": "moderate",
    "onlineStatus": "do_not_disturb"
  },
  "lastUpdated": "2025-08-23T10:30:00Z",
  "dataSource": "slack-userActivitySummary"
}